automata/__init__.py
automata/backend/__init__.py
automata/backend/api/__init__.py
automata/backend/api/main.py
automata/backend/api/routes.py
automata/backend/drawings/automata_drawer.py
automata/backend/grammar/__init__.py
automata/backend/grammar/automaton_base.py
automata/backend/grammar/dist.py
automata/backend/grammar/context_free/__init__.py
automata/backend/grammar/context_free/cfg_mod.py
automata/backend/grammar/context_free/pda/__init__.py
automata/backend/grammar/context_free/pda/pda_mod.py
automata/backend/grammar/context_sensitive/csg_parser.py
automata/backend/grammar/context_sensitive/lba_simulator.py
automata/backend/grammar/logic/buchi_theorem.py
automata/backend/grammar/logic/mso_automata.py
automata/backend/grammar/regular_languages/__init__.py
automata/backend/grammar/regular_languages/regex_to_nfa.py
automata/backend/grammar/regular_languages/dfa/__init__.py
automata/backend/grammar/regular_languages/dfa/dfa_mod.py
automata/backend/grammar/regular_languages/dfa/dfa_mod_algo.py
automata/backend/grammar/regular_languages/dfa/algo/__init__.py
automata/backend/grammar/regular_languages/dfa/algo/kmp.py
automata/backend/grammar/regular_languages/dfa/minimization/hopcroft.py
automata/backend/grammar/regular_languages/dfa/minimization/myhill_nerode.py
automata/backend/grammar/regular_languages/nfa/__init__.py
automata/backend/grammar/regular_languages/nfa/nfa_mod.py
automata/backend/grammar/regular_languages/nfa/nfa_to_dfa.py
automata/backend/grammar/regular_languages/nfa/algo/nfa_bfs.py
automata/backend/grammar/transducers/finite_transducer.py
automata/backend/grammar/transducers/mealy_machine.py
automata/backend/grammar/transducers/scfg_parser.py
automata/backend/theory/kolmogorov.py
automata/backend/theory/recursion_theorem.py
automata/backend/theory/cellular_automata/game_of_life.py
automata/backend/theory/cellular_automata/rule110.py
automata/backend/theory/decidability/presburger.py
automata/backend/theory/decidability/scfg_parser.py
automata_diags-0.2.5.dist-info/METADATA
automata_diags-0.2.5.dist-info/WHEEL
automata_diags-0.2.5.dist-info/licenses/LICENSE
automata_diags-0.2.5.dist-info/RECORD
