Metadata-Version: 2.4
Name: automata_diags
Version: 0.2.5
Summary: 🤖 A powerful, modern, and educational Python toolkit for automata theory. Visualize DFAs, NFAs, CFGs, minimize automata, and more with an elegant, type-safe API.
Project-URL: Homepage, https://github.com/Ajodo-Godson/automata_diags
Project-URL: Bug Tracker, https://github.com/Ajodo-Godson/automata_diags/issues
Project-URL: Documentation, https://automata-diags.readthedocs.io/
Author-email: Godson Ajodo <godson@uni.minerva.edu>
License-File: LICENSE
Keywords: CFG,DFA,NFA,PDA,automata,computer-science,education,finite-automata,formal-languages,graph-theory,visualization
Classifier: Development Status :: 4 - Beta
Classifier: Intended Audience :: Developers
Classifier: Intended Audience :: Education
Classifier: Intended Audience :: Science/Research
Classifier: License :: OSI Approved :: MIT License
Classifier: Operating System :: OS Independent
Classifier: Programming Language :: Python :: 3
Classifier: Programming Language :: Python :: 3.8
Classifier: Programming Language :: Python :: 3.9
Classifier: Programming Language :: Python :: 3.10
Classifier: Programming Language :: Python :: 3.11
Classifier: Programming Language :: Python :: 3.12
Classifier: Topic :: Education
Classifier: Topic :: Scientific/Engineering :: Mathematics
Classifier: Topic :: Scientific/Engineering :: Visualization
Classifier: Topic :: Software Development :: Libraries :: Python Modules
Requires-Python: >=3.8
Requires-Dist: graphviz>=0.20.0
Requires-Dist: pytest>=7.0.0
Provides-Extra: dev
Requires-Dist: black>=24.1.0; extra == 'dev'
Requires-Dist: build>=1.2.0; extra == 'dev'
Requires-Dist: flake8>=7.0.0; extra == 'dev'
Requires-Dist: mypy>=1.8.0; extra == 'dev'
Requires-Dist: pytest-cov>=4.1.0; extra == 'dev'
Requires-Dist: twine>=6.1.0; extra == 'dev'
Requires-Dist: types-graphviz>=0.20.1; extra == 'dev'
Provides-Extra: docs
Requires-Dist: myst-parser>=2.0.0; extra == 'docs'
Requires-Dist: sphinx-rtd-theme>=2.0.0; extra == 'docs'
Requires-Dist: sphinx>=7.2.0; extra == 'docs'
